MANIFEST.in
README.md
requirements.txt
setup.cfg
setup.py
blus/__init__.py
blus/__main__.py
blus/const.py
blus/device.py
blus/mqtt.py
blus/spp.py
blus/spp.xml
blus/util.py
blus.egg-info/PKG-INFO
blus.egg-info/SOURCES.txt
blus.egg-info/dependency_links.txt
blus.egg-info/entry_points.txt
blus.egg-info/requires.txt
blus.egg-info/top_level.txt