Metadata-Version: 1.0
Name: blus
Version: 0.0.18
Summary: Simple Bluez D-Bus client interface
Home-page: https://github.com/molobrakos/blus
Author: Erik
Author-email: error.errorsson@gmail.com
License: UNKNOWN
Keywords: bluez
Platform: UNKNOWN
